RobotFrameworkSelenium/__init__.py
RobotFrameworkSelenium/common.py
RobotFrameworkSelenium/common.pyi
RobotFrameworkSelenium/action/__init__.py
RobotFrameworkSelenium/action/action.py
RobotFrameworkSelenium/action/action.pyi
movoid_robotframework_selenium-1.3.15.dist-info/METADATA
movoid_robotframework_selenium-1.3.15.dist-info/WHEEL
movoid_robotframework_selenium-1.3.15.dist-info/top_level.txt
movoid_robotframework_selenium-1.3.15.dist-info/RECORD
