Metadata-Version: 2.4
Name: movoid_robotframework_selenium
Version: 1.3.15
Home-page: 
Author: movoid
Author-email: bobrobotsun@163.com
Requires-Dist: selenium==4.6.0
Requires-Dist: movoid_debug
Requires-Dist: movoid_function>=1.7.1
Requires-Dist: movoid_robotframework
Requires-Dist: robotframework_selenium2library
Requires-Dist: movoid_package
Requires-Dist: opencv-python
Requires-Dist: lxml
Requires-Dist: cssselect
Dynamic: author
Dynamic: author-email
Dynamic: description
Dynamic: description-content-type
Dynamic: requires-dist
